Tzara_A_Personal_Assistant-1.1.5.data/scripts/startup.sh
Tzara_A_Personal_Assistant-1.1.5.dist-info/DESCRIPTION.rst
Tzara_A_Personal_Assistant-1.1.5.dist-info/METADATA
Tzara_A_Personal_Assistant-1.1.5.dist-info/RECORD
Tzara_A_Personal_Assistant-1.1.5.dist-info/WHEEL
Tzara_A_Personal_Assistant-1.1.5.dist-info/metadata.json
Tzara_A_Personal_Assistant-1.1.5.dist-info/top_level.txt
tzara/Speech.py
tzara/__init__.py
tzara/confirm.py
tzara/converse.py
tzara/database.py
tzara/files.py
tzara/firefox.py
tzara/main.py
tzara/pdf.py
tzara/playmovie.py
tzara/reminder.py
tzara/songs.py
tzara/terminal.py
tzara/tzara.py
