Metadata-Version: 2.0
Name: Tzara-A-Personal-Assistant
Version: 1.1.5
Summary: A Virtual Personal Assistant
Home-page: https://github.com/Suman7495/Tzara---A-Personal-Assistant
Author: Suman Pal
Author-email: suman7495@gmail.com
License: MIT
Platform: UNKNOWN
Classifier: Development Status :: 4 - Beta
Classifier: Programming Language :: Python :: 2.7
